MANIFEST.in
README
README.rst
requirements.txt
setup.cfg
setup.py
redis_structures/__init__.py
redis_structures.egg-info/PKG-INFO
redis_structures.egg-info/SOURCES.txt
redis_structures.egg-info/dependency_links.txt
redis_structures.egg-info/requires.txt
redis_structures.egg-info/top_level.txt
redis_structures/debug/__init__.py
redis_structures/debug/colors.py
redis_structures/debug/stats.py
redis_structures/debug/tlds.py