Metadata-Version: 1.1
Name: redis-structures
Version: 0.1.7
Summary: Redis data structures wrapped with Python 3.
Home-page: https://github.com/jaredlunde/redis_structures
Author: Jared Lunde
Author-email: jared.lunde@gmail.com
License: MIT
Keywords: redis,data structures
Platform: UNKNOWN
Classifier: Development Status :: 5 - Production/Stable
Classifier: Intended Audience :: Developers
Classifier: Topic :: Software Development :: Build Tools
Classifier: License :: OSI Approved :: MIT License
Classifier: Programming Language :: Python :: 3.3
Classifier: Programming Language :: Python :: 3.4
Classifier: Programming Language :: Python :: 3.5
